petrolprices/__init__.py
petrolprices/petrolprices.py
petrolprices/py.typed
petrolprices/types.py
petrolprices_sdk-0.2.2.dist-info/METADATA
petrolprices_sdk-0.2.2.dist-info/WHEEL
petrolprices_sdk-0.2.2.dist-info/licenses/LICENSE.md
petrolprices_sdk-0.2.2.dist-info/RECORD
