Metadata-Version: 2.1
Name: petrolprices-sdk
Version: 0.2.2
Summary: PetrolPrices Python SDK
Project-URL: Source Code, https://github.com/owenvoke/petrolprices-python-sdk
Project-URL: Issues, https://github.com/owenvoke/petrolprices-python-sdk/issues
Author-email: Owen Voke <development@voke.dev>
License-Expression: MIT
License-File: LICENSE.md
Keywords: petrolprices,sdk
Classifier: Intended Audience :: Developers
Classifier: License :: OSI Approved :: MIT License
Classifier: Programming Language :: Python :: 3 :: Only
Requires-Python: >=3.11.1
Requires-Dist: requests>=2.28.1
